imperiumengine/__init__.py
imperiumengine/config/__init__.py
imperiumengine/config/config_loader.py
imperiumengine/config/logger.py
imperiumengine/config/settings.py
imperiumengine/indicators/__init__.py
imperiumengine/indicators/atr.py
imperiumengine/indicators/base_indicator.py
imperiumengine/indicators/bollinger_bands.py
imperiumengine/indicators/ema.py
imperiumengine/indicators/macd.py
imperiumengine/indicators/rsi.py
imperiumengine/indicators/vwap.py
imperiumengine/py.typed
imperiumengine/services/__init__.py
imperiumengine/services/price_service.py
imperiumengine-0.1.0.dist-info/METADATA
imperiumengine-0.1.0.dist-info/WHEEL
imperiumengine-0.1.0.dist-info/RECORD
