Metadata-Version: 2.3
Name: imperiumengine
Version: 0.1.0
Summary: add
Author: luiz correa (zcorrea357)
Author-email: zcorrea357@gmail.com
Requires-Python: >=3.13,<4.0
Classifier: Programming Language :: Python :: 3
Classifier: Programming Language :: Python :: 3.13
Requires-Dist: numpy (>=2.2.2,<3.0.0)
Requires-Dist: pandas (>=2.2.3,<3.0.0)
Requires-Dist: sqlalchemy (>=2.0.37,<3.0.0)
Project-URL: Documentation, https://github.com/ImperiumSyndicate/ImperiumEngine
Project-URL: Homepage, https://github.com/ImperiumSyndicate/ImperiumEngine
Project-URL: changelog, https://github.com/ImperiumSyndicate/ImperiumEngine/blob/main/CHANGELOG.md
Project-URL: issues, https://github.com/ImperiumSyndicate/ImperiumEngine/issues
Project-URL: releasenotes, https://github.com/ImperiumSyndicate/ImperiumEngine/releases
Project-URL: source, https://github.com/ImperiumSyndicate/ImperiumEngine
